flink_job_manager_api/__init__.py
flink_job_manager_api/api/__init__.py
flink_job_manager_api/api/default/__init__.py
flink_job_manager_api/api/default/cancel_job.py
flink_job_manager_api/api/default/delete_cluster_data_set.py
flink_job_manager_api/api/default/delete_jar.py
flink_job_manager_api/api/default/generate_plan_from_jar.py
flink_job_manager_api/api/default/get_aggregated_job_metrics.py
flink_job_manager_api/api/default/get_aggregated_subtask_metrics.py
flink_job_manager_api/api/default/get_aggregated_task_manager_metrics.py
flink_job_manager_api/api/default/get_checkpoint_config.py
flink_job_manager_api/api/default/get_checkpoint_statistic_details.py
flink_job_manager_api/api/default/get_checkpoint_status.py
flink_job_manager_api/api/default/get_checkpointing_statistics.py
flink_job_manager_api/api/default/get_cluster_configuration_info.py
flink_job_manager_api/api/default/get_cluster_data_set_delete_status.py
flink_job_manager_api/api/default/get_cluster_data_set_list.py
flink_job_manager_api/api/default/get_cluster_overview.py
flink_job_manager_api/api/default/get_dashboard_configuration.py
flink_job_manager_api/api/default/get_jar_list.py
flink_job_manager_api/api/default/get_job_accumulators.py
flink_job_manager_api/api/default/get_job_config.py
flink_job_manager_api/api/default/get_job_details.py
flink_job_manager_api/api/default/get_job_exceptions.py
flink_job_manager_api/api/default/get_job_execution_result.py
flink_job_manager_api/api/default/get_job_ids_with_statuses_overview.py
flink_job_manager_api/api/default/get_job_manager_environment.py
flink_job_manager_api/api/default/get_job_manager_job_configuration.py
flink_job_manager_api/api/default/get_job_manager_job_environment.py
flink_job_manager_api/api/default/get_job_manager_log_list.py
flink_job_manager_api/api/default/get_job_manager_log_url.py
flink_job_manager_api/api/default/get_job_manager_metrics.py
flink_job_manager_api/api/default/get_job_manager_operator_metrics.py
flink_job_manager_api-1.0.2.dist-info/LICENSE
flink_job_manager_api-1.0.2.dist-info/METADATA
flink_job_manager_api-1.0.2.dist-info/WHEEL
flink_job_manager_api-1.0.2.dist-info/RECORD
